fptai_chatbot_sdk/__init__.py
fptai_chatbot_sdk/constant.py
fptai_chatbot_sdk/manage.py
fptai_chatbot_sdk/models.py
fptai_chatbot_sdk-1.0.1.dist-info/LICENSE
fptai_chatbot_sdk-1.0.1.dist-info/METADATA
fptai_chatbot_sdk-1.0.1.dist-info/WHEEL
fptai_chatbot_sdk-1.0.1.dist-info/top_level.txt
fptai_chatbot_sdk-1.0.1.dist-info/RECORD
