Metadata-Version: 2.1
Name: fptai-chatbot-sdk
Version: 1.0.1
Summary: SDK for chat bot
Home-page: https://github.com/pypa/sampleproject
Author: Trinh Kim Tuan
Author-email: tuantk2@fpt.com.vn
License: UNKNOWN
Platform: UNKNOWN
Classifier: Programming Language :: Python :: 3
Classifier: License :: OSI Approved :: MIT License
Classifier: Operating System :: OS Independent
Requires-Python: >=3.6
